recognize/__init__.py
recognize/commands/__init__.py
recognize/commands/lib/__init__.py
recognize/commands/lib/client.py
recognize/commands/lib/entries.py
recognize/commands/lib/helpers.py
recognize/commands/search.py
recognize/commands/upload.py
recognize/main.py
recognize-0.1.25.dist-info/METADATA
recognize-0.1.25.dist-info/WHEEL
recognize-0.1.25.dist-info/entry_points.txt
recognize-0.1.25.dist-info/RECORD
